sqlalchemy_fields/__init__.py
sqlalchemy_fields/exceptions.py
sqlalchemy_fields/storages/__init__.py
sqlalchemy_fields/storages/base.py
sqlalchemy_fields/storages/filesystem.py
sqlalchemy_fields/storages/s3.py
sqlalchemy_fields/storages/utils.py
sqlalchemy_fields/types/__init__.py
sqlalchemy_fields/types/email.py
sqlalchemy_fields/types/file.py
sqlalchemy_fields/types/image.py
sqlalchemy_fields/types/ip.py
sqlalchemy_fields/types/url.py
sqlalchemy_fields/types/uuid.py
sqlalchemy_fields-0.5.0.dist-info/METADATA
sqlalchemy_fields-0.5.0.dist-info/WHEEL
sqlalchemy_fields-0.5.0.dist-info/licenses/LICENSE.txt
sqlalchemy_fields-0.5.0.dist-info/RECORD
