Metadata-Version: 2.1
Name: sqlalchemy-fields
Version: 0.5.0
Summary: SQLAlchemy fields
Project-URL: Documentation, https://github.com/aminalaee/sqlalchemy-fields#readme
Project-URL: Issues, https://github.com/aminalaee/sqlalchemy-fields/issues
Project-URL: Source, https://github.com/aminalaee/sqlalchemy-fields
Author-email: Amin Alaee <me@aminalaee.dev>
License-Expression: MIT
License-File: LICENSE.txt
Keywords: django,orm,sqlalchemy
Classifier: Development Status :: 4 - Beta
Classifier: Programming Language :: Python
Classifier: Programming Language :: Python :: 3.7
Classifier: Programming Language :: Python :: 3.8
Classifier: Programming Language :: Python :: 3.9
Classifier: Programming Language :: Python :: 3.10
Classifier: Programming Language :: Python :: 3.11
Classifier: Topic :: Database
Classifier: Topic :: Database :: Database Engines/Servers
Classifier: Topic :: Internet
Classifier: Topic :: Internet :: WWW/HTTP
Classifier: Topic :: Internet :: WWW/HTTP :: HTTP Servers
Classifier: Typing :: Typed
Requires-Python: >=3.7
Requires-Dist: sqlalchemy>=1.4
Provides-Extra: full
Requires-Dist: boto3~=1.25; extra == 'full'
Requires-Dist: email-validator~=1.3; extra == 'full'
Requires-Dist: pillow~=9.4; extra == 'full'
